LICENSE
MANIFEST.in
README.md
reactobus
setup.py
ReactOBus/__init__.py
ReactOBus/core.py
ReactOBus/db.py
ReactOBus/inputs.py
ReactOBus/outputs.py
ReactOBus/reactor.py
ReactOBus/utils.py
ReactOBus.egg-info/PKG-INFO
ReactOBus.egg-info/SOURCES.txt
ReactOBus.egg-info/dependency_links.txt
ReactOBus.egg-info/requires.txt
ReactOBus.egg-info/top_level.txt
share/examples/lava.local.yaml
share/examples/lava.yaml
share/examples/push.py
share/examples/react.sh
share/examples/reactobus.yaml
share/examples/sub.py